<?xml version="1.0" encoding="UTF-8"?>
<list xmlns:xsi="http://www.w3.org/2001/XMLSchema-instance" xsi:noNamespaceSchemaLocation="../../../xsd/optionsData.xsd">
	<option id="37200" name="chaos_aug_2">
		<!-- Attribute Attack +30 -->
		<passive_skill id="37130" level="3" />
	</option>
	<option id="37201" name="chaos_aug_2">
		<!-- Attribute Attack +40 -->
		<passive_skill id="37130" level="4" />
	</option>
	<option id="37202" name="chaos_aug_2">
		<!-- Attribute Attack +50 -->
		<passive_skill id="37130" level="5" />
	</option>
	<option id="37203" name="chaos_aug_2">
		<!-- Attribute Resistance +10 -->
		<passive_skill id="37131" level="1" />
	</option>
	<option id="37204" name="chaos_aug_2">
		<!-- Attribute Resistance +20 -->
		<passive_skill id="37131" level="2" />
	</option>
	<option id="37205" name="chaos_aug_2">
		<!-- Attribute Resistance +30 -->
		<passive_skill id="37131" level="3" />
	</option>
	<option id="37206" name="chaos_aug_2">
		<!-- Attribute Resistance +40 -->
		<passive_skill id="37131" level="4" />
	</option>
	<option id="37207" name="chaos_aug_2">
		<!-- Attribute Resistance +50 -->
		<passive_skill id="37131" level="5" />
	</option>
	<option id="37208" name="chaos_aug_2">
		<!-- Critical Damage for basic attacks +2% -->
		<passive_skill id="37132" level="1" />
	</option>
	<option id="37209" name="chaos_aug_2">
		<!-- Critical Damage for basic attacks +4% -->
		<passive_skill id="37132" level="2" />
	</option>
	<option id="37210" name="chaos_aug_2">
		<!-- Critical Damage for basic attacks +6% -->
		<passive_skill id="37132" level="3" />
	</option>
	<option id="37211" name="chaos_aug_2">
		<!-- Critical Damage for basic attacks +8% -->
		<passive_skill id="37132" level="4" />
	</option>
	<option id="37212" name="chaos_aug_2">
		<!-- Critical Damage for basic attacks +10% -->
		<passive_skill id="37132" level="5" />
	</option>
	<option id="37213" name="chaos_aug_2">
		<!-- P. Skill Critical Damage +2% -->
		<passive_skill id="37133" level="1" />
	</option>
	<option id="37214" name="chaos_aug_2">
		<!-- P. Skill Critical Damage +4% -->
		<passive_skill id="37133" level="2" />
	</option>
	<option id="37215" name="chaos_aug_2">
		<!-- P. Skill Critical Damage +6% -->
		<passive_skill id="37133" level="3" />
	</option>
	<option id="37216" name="chaos_aug_2">
		<!-- P. Skill Critical Damage +8% -->
		<passive_skill id="37133" level="4" />
	</option>
	<option id="37217" name="chaos_aug_2">
		<!-- P. Skill Critical Damage +10% -->
		<passive_skill id="37133" level="5" />
	</option>
	<option id="37218" name="chaos_aug_2">
		<!-- M. Skill Critical Damage +2% -->
		<passive_skill id="37134" level="1" />
	</option>
	<option id="37219" name="chaos_aug_2">
		<!-- M. Skill Critical Damage +4% -->
		<passive_skill id="37134" level="2" />
	</option>
	<option id="37220" name="chaos_aug_2">
		<!-- M. Skill Critical Damage +6% -->
		<passive_skill id="37134" level="3" />
	</option>
	<option id="37221" name="chaos_aug_2">
		<!-- M. Skill Critical Damage +8% -->
		<passive_skill id="37134" level="4" />
	</option>
	<option id="37222" name="chaos_aug_2">
		<!-- M. Skill Critical Damage +10% -->
		<passive_skill id="37134" level="5" />
	</option>
	<option id="37223" name="chaos_aug_2">
		<!-- P. Def. +2% -->
		<passive_skill id="37135" level="1" />
	</option>
	<option id="37224" name="chaos_aug_2">
		<!-- P. Def. +4% -->
		<passive_skill id="37135" level="2" />
	</option>
	<option id="37225" name="chaos_aug_2">
		<!-- P. Def. +6% -->
		<passive_skill id="37135" level="3" />
	</option>
	<option id="37226" name="chaos_aug_2">
		<!-- P. Def. +8% -->
		<passive_skill id="37135" level="4" />
	</option>
	<option id="37227" name="chaos_aug_2">
		<!-- P. Def. +10% -->
		<passive_skill id="37135" level="5" />
	</option>
	<option id="37228" name="chaos_aug_2">
		<!-- M. Def. +2% -->
		<passive_skill id="37136" level="1" />
	</option>
	<option id="37229" name="chaos_aug_2">
		<!-- M. Def. +4% -->
		<passive_skill id="37136" level="2" />
	</option>
	<option id="37230" name="chaos_aug_2">
		<!-- M. Def. +6% -->
		<passive_skill id="37136" level="3" />
	</option>
	<option id="37231" name="chaos_aug_2">
		<!-- M. Def. +8% -->
		<passive_skill id="37136" level="4" />
	</option>
	<option id="37232" name="chaos_aug_2">
		<!-- M. Def. +10% -->
		<passive_skill id="37136" level="5" />
	</option>
	<option id="37233" name="chaos_aug_2">
		<!-- Bow/ Crossbow Resistance +2% -->
		<passive_skill id="37137" level="1" />
	</option>
	<option id="37234" name="chaos_aug_2">
		<!-- Bow/ Crossbow Resistance +4% -->
		<passive_skill id="37137" level="2" />
	</option>
	<option id="37235" name="chaos_aug_2">
		<!-- Bow/ Crossbow Resistance +6% -->
		<passive_skill id="37137" level="3" />
	</option>
	<option id="37236" name="chaos_aug_2">
		<!-- Bow/ Crossbow Resistance +8% -->
		<passive_skill id="37137" level="4" />
	</option>
	<option id="37237" name="chaos_aug_2">
		<!-- Bow/ Crossbow Resistance +10% -->
		<passive_skill id="37137" level="5" />
	</option>
	<option id="37238" name="chaos_aug_2">
		<!-- Dagger/ Dual Daggers Resistance +2% -->
		<passive_skill id="37138" level="1" />
	</option>
	<option id="37239" name="chaos_aug_2">
		<!-- Dagger/ Dual Daggers Resistance +4% -->
		<passive_skill id="37138" level="2" />
	</option>
	<option id="37240" name="chaos_aug_2">
		<!-- Dagger/ Dual Daggers Resistance +6% -->
		<passive_skill id="37138" level="3" />
	</option>
	<option id="37241" name="chaos_aug_2">
		<!-- Dagger/ Dual Daggers Resistance +8% -->
		<passive_skill id="37138" level="4" />
	</option>
	<option id="37242" name="chaos_aug_2">
		<!-- Dagger/ Dual Daggers Resistance +10% -->
		<passive_skill id="37138" level="5" />
	</option>
	<option id="37243" name="chaos_aug_2">
		<!-- Sword/ Dual Swords Resistance +2% -->
		<passive_skill id="37139" level="1" />
	</option>
	<option id="37244" name="chaos_aug_2">
		<!-- Sword/ Dual Swords Resistance +4% -->
		<passive_skill id="37139" level="2" />
	</option>
	<option id="37245" name="chaos_aug_2">
		<!-- Sword/ Dual Swords Resistance +6% -->
		<passive_skill id="37139" level="3" />
	</option>
	<option id="37246" name="chaos_aug_2">
		<!-- Sword/ Dual Swords Resistance +8% -->
		<passive_skill id="37139" level="4" />
	</option>
	<option id="37247" name="chaos_aug_2">
		<!-- Sword/ Dual Swords Resistance +10% -->
		<passive_skill id="37139" level="5" />
	</option>
	<option id="37248" name="chaos_aug_2">
		<!-- Debuff Resistance +2% -->
		<passive_skill id="37140" level="1" />
	</option>
	<option id="37249" name="chaos_aug_2">
		<!-- Debuff Resistance +4% -->
		<passive_skill id="37140" level="2" />
	</option>
	<option id="37250" name="chaos_aug_2">
		<!-- Debuff Resistance +6% -->
		<passive_skill id="37140" level="3" />
	</option>
	<option id="37251" name="chaos_aug_2">
		<!-- Debuff Resistance +8% -->
		<passive_skill id="37140" level="4" />
	</option>
	<option id="37252" name="chaos_aug_2">
		<!-- Debuff Resistance +10% -->
		<passive_skill id="37140" level="5" />
	</option>
	<option id="37253" name="chaos_aug_2">
		<!-- Received Healing +2% -->
		<passive_skill id="37141" level="1" />
	</option>
	<option id="37254" name="chaos_aug_2">
		<!-- Received Healing +4% -->
		<passive_skill id="37141" level="2" />
	</option>
	<option id="37255" name="chaos_aug_2">
		<!-- Received Healing +6% -->
		<passive_skill id="37141" level="3" />
	</option>
	<option id="37256" name="chaos_aug_2">
		<!-- Received Healing +8% -->
		<passive_skill id="37141" level="4" />
	</option>
	<option id="37257" name="chaos_aug_2">
		<!-- Received Healing +10% -->
		<passive_skill id="37141" level="5" />
	</option>
	<option id="37258" name="chaos_aug_2">
		<!-- Skill cooldown -1% -->
		<passive_skill id="37142" level="1" />
	</option>
	<option id="37259" name="chaos_aug_2">
		<!-- Skill Cooldown -2% -->
		<passive_skill id="37142" level="2" />
	</option>
	<option id="37260" name="chaos_aug_2">
		<!-- Skill cooldown -3% -->
		<passive_skill id="37142" level="3" />
	</option>
	<option id="37261" name="chaos_aug_2">
		<!-- Skill Cooldown -4% -->
		<passive_skill id="37142" level="4" />
	</option>
	<option id="37262" name="chaos_aug_2">
		<!-- Skill Cooldown -5% -->
		<passive_skill id="37142" level="5" />
	</option>
	<option id="37263" name="chaos_aug_2">
		<!-- Acquired XP/ SP +2% -->
		<passive_skill id="37143" level="1" />
	</option>
	<option id="37264" name="chaos_aug_2">
		<!-- Acquired XP/ SP +4% -->
		<passive_skill id="37143" level="2" />
	</option>
	<option id="37265" name="chaos_aug_2">
		<!-- Acquired XP/ SP +6% -->
		<passive_skill id="37143" level="3" />
	</option>
	<option id="37266" name="chaos_aug_2">
		<!-- Acquired XP/ SP +8% -->
		<passive_skill id="37143" level="4" />
	</option>
	<option id="37267" name="chaos_aug_2">
		<!-- Acquired XP/ SP +10% -->
		<passive_skill id="37143" level="5" />
	</option>
	<option id="37268" name="chaos_aug_2">
		<!-- P. Skill Power +10% -->
		<passive_skill id="37144" level="1" />
	</option>
	<option id="37269" name="chaos_aug_2">
		<!-- P. Skill Power +15% -->
		<passive_skill id="37144" level="2" />
	</option>
	<option id="37270" name="chaos_aug_2">
		<!-- P. Skill Power +20% -->
		<passive_skill id="37144" level="3" />
	</option>
	<option id="37271" name="chaos_aug_2">
		<!-- M. Skill Power +10% -->
		<passive_skill id="37145" level="1" />
	</option>
	<option id="37272" name="chaos_aug_2">
		<!-- M. Skill Power +15% -->
		<passive_skill id="37145" level="2" />
	</option>
	<option id="37273" name="chaos_aug_2">
		<!-- M. Skill Power +20% -->
		<passive_skill id="37145" level="3" />
	</option>
	<option id="37274" name="chaos_aug_2">
		<!-- Critical Damage for basic attacks +17% -->
		<passive_skill id="37146" level="1" />
	</option>
	<option id="37275" name="chaos_aug_2">
		<!-- Critical Damage for basic attacks +20% -->
		<passive_skill id="37146" level="2" />
	</option>
	<option id="37276" name="chaos_aug_2">
		<!-- Critical Damage for basic attacks +23% -->
		<passive_skill id="37146" level="3" />
	</option>
	<option id="37277" name="chaos_aug_2">
		<!-- P. Skill Critical Damage +17% -->
		<passive_skill id="37147" level="1" />
	</option>
	<option id="37278" name="chaos_aug_2">
		<!-- P. Skill Critical Damage +20% -->
		<passive_skill id="37147" level="2" />
	</option>
	<option id="37279" name="chaos_aug_2">
		<!-- P. Skill Critical Damage +23% -->
		<passive_skill id="37147" level="3" />
	</option>
	<option id="37280" name="chaos_aug_2">
		<!-- M. Skill Critical Damage +17% -->
		<passive_skill id="37148" level="1" />
	</option>
	<option id="37281" name="chaos_aug_2">
		<!-- M. Skill Critical Damage +20% -->
		<passive_skill id="37148" level="2" />
	</option>
	<option id="37282" name="chaos_aug_2">
		<!-- M. Skill Critical Damage +23% -->
		<passive_skill id="37148" level="3" />
	</option>
	<option id="37283" name="chaos_aug_2">
		<!-- Fixed Damage Resistance +17% -->
		<passive_skill id="37149" level="1" />
	</option>
	<option id="37284" name="chaos_aug_2">
		<!-- Fixed Damage Resistance +20% -->
		<passive_skill id="37149" level="2" />
	</option>
	<option id="37285" name="chaos_aug_2">
		<!-- Received damage when immobilized -20% -->
		<passive_skill id="37150" level="1" />
	</option>
	<option id="37286" name="chaos_aug_2">
		<!-- Damage +15% -->
		<passive_skill id="37151" level="1" />
	</option>
	<option id="37287" name="chaos_aug_2">
		<!-- Damage +20% -->
		<passive_skill id="37151" level="2" />
	</option>
	<option id="37288" name="chaos_aug_2">
		<!-- Received damage -15% -->
		<passive_skill id="37152" level="1" />
	</option>
	<option id="37289" name="chaos_aug_2">
		<!-- Received damage -20% -->
		<passive_skill id="37152" level="2" />
	</option>
	<option id="37290" name="chaos_aug_3">
		<!-- Damage +10%, Accuracy +20 -->
		<passive_skill id="37153" level="1" />
	</option>
	<option id="37291" name="chaos_aug_3">
		<!-- All Critical Damage +10%, Accuracy +20 -->
		<passive_skill id="37154" level="1" />
	</option>
	<option id="37292" name="chaos_aug_3">
		<!-- Skill Power +10%, Accuracy +20 -->
		<passive_skill id="37155" level="1" />
	</option>
	<option id="37293" name="Collection_6_493">
		<!-- Damage +1%, received damage -1% -->
		<passive_skill id="37157" level="1" />
	</option>
	<option id="37294" name="Collection_6_494">
		<!-- Damage +1%, received damage -1% -->
		<passive_skill id="37158" level="1" />
	</option>
	<option id="37295" name="Collection_6_495">
		<!-- Damage +1%, received damage -1% -->
		<passive_skill id="37159" level="1" />
	</option>
</list>